ErrorType/__init__.py
ErrorType/error_type.py
ErrorType/stat_chart.py
ErrorType-0.1.3.dist-info/LICENSE.txt
ErrorType-0.1.3.dist-info/METADATA
ErrorType-0.1.3.dist-info/WHEEL
ErrorType-0.1.3.dist-info/top_level.txt
ErrorType-0.1.3.dist-info/RECORD
