Metadata-Version: 2.1
Name: ErrorType
Version: 0.1.3
Summary: Error type analysis
Home-page: https://github.com/JOE881003/Error-type-analysis
Author: YUKAILIAO
Author-email: joe881003@gmail.com
Classifier: Programming Language :: Python :: 3
Classifier: License :: OSI Approved :: MIT License
Classifier: Operating System :: OS Independent
Requires-Python: >=3.6
License-File: LICENSE.txt
